audio_utils/__init__.py
audio_utils/audio_segment.py
audio_utils/mp3_utility.py
audio_utils-0.0.1.dist-info/METADATA
audio_utils-0.0.1.dist-info/RECORD
audio_utils-0.0.1.dist-info/WHEEL
audio_utils-0.0.1.dist-info/top_level.txt
