Metadata-Version: 2.1
Name: audio-utils
Version: 0.0.1
Summary: Miscellaneous audio processing scripts.
Home-page: https://github.com/sanskrit-coders/audio_utils
Author: Sanskrit programmers
Author-email: sanskrit-programmers@googlegroups.com
License: MIT
Keywords: audio internet-archive
Platform: UNKNOWN
Classifier: Development Status :: 5 - Production/Stable
Classifier: Intended Audience :: Education
Classifier: Topic :: Text Processing :: Linguistic
Classifier: License :: OSI Approved :: MIT License
Classifier: Programming Language :: Python :: 3
Classifier: Programming Language :: Python :: 3.7
Provides-Extra: test
Requires-Dist: pydub
Requires-Dist: ffmpy
Requires-Dist: eyed3
Requires-Dist: mutagen
Provides-Extra: test
Requires-Dist: pytest; extra == 'test'
